sulguk/__init__.py
sulguk/aiogram_middleware.py
sulguk/data.py
sulguk/mapper.py
sulguk/py.typed
sulguk/walker.py
sulguk/wrapper.py
sulguk/entities/__init__.py
sulguk/entities/base.py
sulguk/entities/decoration.py
sulguk/entities/emoji.py
sulguk/entities/list.py
sulguk/entities/no_contents.py
sulguk/entities/progress.py
sulguk/entities/stub.py
sulguk/entities/text.py
sulguk/post_manager/__init__.py
sulguk/post_manager/chat_info.py
sulguk/post_manager/cli.py
sulguk/post_manager/editor.py
sulguk/post_manager/exceptions.py
sulguk/post_manager/file.py
sulguk/post_manager/links.py
sulguk/post_manager/params.py
sulguk/post_manager/sender.py
sulguk/render/__init__.py
sulguk/render/canvas.py
sulguk/render/numbers.py
sulguk/render/state.py
sulguk-0.11.1.dist-info/licenses/LICENSE
sulguk2/canvas/__init__.py
sulguk2/canvas/state.py
sulguk-0.11.1.dist-info/METADATA
sulguk-0.11.1.dist-info/WHEEL
sulguk-0.11.1.dist-info/entry_points.txt
sulguk-0.11.1.dist-info/top_level.txt
sulguk-0.11.1.dist-info/RECORD
