Metadata-Version: 2.4
Name: sulguk
Version: 0.11.1
Summary: Converter HTML to Telegram Entities
Author-email: Andrey Tikhonov <17@itishka.org>
License:                                  Apache License
Project-URL: Homepage, https://github.com/tishka17/sulguk
Project-URL: Bug Tracker, https://github.com/tishka17/sulguk/issues
Classifier: Programming Language :: Python :: 3
Classifier: License :: OSI Approved :: Apache Software License
Classifier: Operating System :: OS Independent
Requires-Python: >=3.10
License-File: LICENSE
Requires-Dist: html5lib~=1.0
Requires-Dist: lxml
Provides-Extra: cli
Requires-Dist: aiogram; extra == "cli"
Dynamic: license-file
